SMPyBandits/LICENSE
SMPyBandits/README.rst
SMPyBandits/__init__.py
SMPyBandits/complete_tree_exploration_for_MP_bandits.py
SMPyBandits/configuration.py
SMPyBandits/configuration_all_singleplayer.py
SMPyBandits/configuration_comparing_aggregation_algorithms.py
SMPyBandits/configuration_comparing_doubling_algorithms.py
SMPyBandits/configuration_markovian.py
SMPyBandits/configuration_multiplayers.py
SMPyBandits/configuration_multiplayers_nonstationary.py
SMPyBandits/configuration_multiplayers_with_aggregation.py
SMPyBandits/configuration_nonstationary.py
SMPyBandits/configuration_sparse.py
SMPyBandits/configuration_sparse_multiplayers.py
SMPyBandits/env_client.py
SMPyBandits/example_of_configuration_multiplayers.py
SMPyBandits/example_of_configuration_singleplayer.py
SMPyBandits/example_of_main_multiplayers_more.py
SMPyBandits/example_of_main_singleplayer.py
SMPyBandits/main.py
SMPyBandits/main_multiplayers.py
SMPyBandits/main_multiplayers_more.py
SMPyBandits/main_sparse_multiplayers.py
SMPyBandits/policy_server.py
SMPyBandits/save_configuration_for_reproducibility.py
SMPyBandits/very_simple_configuration.py
SMPyBandits/Arms/Arm.py
SMPyBandits/Arms/Bernoulli.py
SMPyBandits/Arms/Binomial.py
SMPyBandits/Arms/Constant.py
SMPyBandits/Arms/DiscreteArm.py
SMPyBandits/Arms/Exponential.py
SMPyBandits/Arms/Gamma.py
SMPyBandits/Arms/Gaussian.py
SMPyBandits/Arms/Poisson.py
SMPyBandits/Arms/UniformArm.py
SMPyBandits/Arms/__init__.py
SMPyBandits/Arms/kullback.py
SMPyBandits/Arms/usenumba.py
SMPyBandits/Environment/CollisionModels.py
SMPyBandits/Environment/Evaluator.py
SMPyBandits/Environment/EvaluatorMultiPlayers.py
SMPyBandits/Environment/EvaluatorSparseMultiPlayers.py
SMPyBandits/Environment/MAB.py
SMPyBandits/Environment/Result.py
SMPyBandits/Environment/ResultMultiPlayers.py
SMPyBandits/Environment/__init__.py
SMPyBandits/Environment/fairnessMeasures.py
SMPyBandits/Environment/memory_consumption.py
SMPyBandits-0.9.6.dist-info/DESCRIPTION.rst
SMPyBandits-0.9.6.dist-info/METADATA
SMPyBandits-0.9.6.dist-info/RECORD
SMPyBandits-0.9.6.dist-info/WHEEL
SMPyBandits-0.9.6.dist-info/metadata.json
SMPyBandits-0.9.6.dist-info/top_level.txt
