Metadata-Version: 2.0
Name: SMPyBandits
Version: 0.9.6
Summary: SMPyBandits: Open-Source Python package for Single- and Multi-Players multi-armed Bandits algorithms.
Home-page: https://github.com/SMPyBandits/SMPyBandits/
Author: Lilian Besson
Author-email: naereen@crans.org
License: MIT
Download-URL: https://github.com/SMPyBandits/SMPyBandits/releases/
Project-URL: Bug Reports, https://github.com/SMPyBandits/SMPyBandits/issues
Project-URL: Source, https://github.com/SMPyBandits/SMPyBandits/tree/master/
Project-URL: Documentation, https://smpybandits.github.io/
Keywords: multi-arm-bandits simulations learning-theory centralized-algorithms decentralized-algorithms cognitive-radio
Platform: GNU/Linux
Classifier: Development Status :: 4 - Beta
Classifier: Environment :: Console
Classifier: Intended Audience :: Science/Research
Classifier: License :: OSI Approved :: MIT License
Classifier: Natural Language :: English
Classifier: Operating System :: Unix
Classifier: Programming Language :: Python :: 2.7
Classifier: Programming Language :: Python :: 3.4
Classifier: Programming Language :: Python :: 3.5
Classifier: Programming Language :: Python :: 3.6
Classifier: Topic :: Scientific/Engineering
Classifier: Topic :: Scientific/Engineering :: Mathematics
Provides-Extra: full
Provides-Extra: doc
Requires-Dist: numpy
Requires-Dist: scipy (>0.9)
Requires-Dist: matplotlib (>=2)
Requires-Dist: joblib
Requires-Dist: seaborn
Requires-Dist: scikit-learn
Requires-Dist: scikit-optimize
Provides-Extra: doc
Requires-Dist: sphinx-rtd-theme; extra == 'doc'
Requires-Dist: recommonmark; extra == 'doc'
Requires-Dist: nbsphinx; extra == 'doc'
Requires-Dist: pyreverse; extra == 'doc'
Provides-Extra: full
Requires-Dist: tqdm; extra == 'full'
Requires-Dist: numba; extra == 'full'
Requires-Dist: docopt; extra == 'full'
Requires-Dist: ipython; extra == 'full'
